recent.py
recent-0.1.3.dist-info/DESCRIPTION.rst
recent-0.1.3.dist-info/METADATA
recent-0.1.3.dist-info/RECORD
recent-0.1.3.dist-info/WHEEL
recent-0.1.3.dist-info/entry_points.txt
recent-0.1.3.dist-info/metadata.json
recent-0.1.3.dist-info/top_level.txt
