Metadata-Version: 2.0
Name: recent
Version: 0.1.3
Summary: log bash history to an sqlite database
Home-page: https://github.com/trengrj/recent
Author: John Trengrove
Author-email: john@retrofilter.com
License: MIT
Keywords: logging bash history database
Platform: UNKNOWN
Classifier: Development Status :: 3 - Alpha
Classifier: Intended Audience :: Developers
Classifier: Environment :: Console
Classifier: Topic :: System :: Logging
Classifier: License :: OSI Approved :: MIT License
Classifier: Programming Language :: Python :: 2
Classifier: Programming Language :: Python :: 2.7
Classifier: Programming Language :: Python :: 3
Classifier: Programming Language :: Python :: 3.3
Classifier: Programming Language :: Python :: 3.4
Classifier: Programming Language :: Python :: 3.5
